one_shot_calculator/__init__.py
one_shot_calculator/discrete_dists.py
one_shot_calculator/one_shot_calculator_3p5.py
one_shot_calculator/one_shot_calculator_adnd.py
one_shot_calculator/process_csv.py
one_shot_calculator/csv/Monster Compendium (Graphless).csv
one_shot_calculator/csv/SBLaxman's AD&D Monster List 2.1.csv
one_shot_calculator/csv/__init__.py
one_shot_calculator-1.0.1.dist-info/METADATA
one_shot_calculator-1.0.1.dist-info/WHEEL
one_shot_calculator-1.0.1.dist-info/licenses/LICENSE
one_shot_calculator-1.0.1.dist-info/RECORD
