Metadata-Version: 2.4
Name: one_shot_calculator
Version: 1.0.1
Summary: A package to calculate the probability of one-shotting monsters in Dungeons and Dragons
Project-URL: Homepage, https://github.com/matt-vonhippel/one-shot-calculator
Project-URL: Issues, https://github.com/matt-vonhippel/one-shot-calculator/issues
Author: Matt von Hippel
License-File: LICENSE
Classifier: License :: OSI Approved :: MIT License
Classifier: Operating System :: OS Independent
Classifier: Programming Language :: Python :: 3
Requires-Python: >=3.9
Requires-Dist: charset-normalizer
Requires-Dist: frozendict
Requires-Dist: numpy
Requires-Dist: pandas
Requires-Dist: plotly
